{
  "@type": "AnnotationStore",
  "@id": "IDD493A33",
  "resources": [
    {
      "@type": "TextResource",
      "@id": "DB0D",
      "@include": "../../base/DB0D.txt"
    }
  ],
  "annotationsets": [
    {
      "@type": "AnnotationDataSet",
      "@id": "Translation",
      "keys": [
        {
          "@type": "DataKey",
          "@id": "root_idx_mapping"
        },
        {
          "@type": "DataKey",
          "@id": "Translation_Segment"
        }
      ],
      "data": [
        {
          "@type": "AnnotationData",
          "@id": "CC2C2357",
          "key": "root_idx_mapping",
          "value": {
            "@type": "String",
            "value": "1"
          }
        },
        {
          "@type": "AnnotationData",
          "@id": "F5A84DFB",
          "key": "Translation_Segment",
          "value": {
            "@type": "String",
            "value": "Italian_Segment"
          }
        },
        {
          "@type": "AnnotationData",
          "@id": "6F83194C",
          "key": "root_idx_mapping",
          "value": {
            "@type": "String",
            "value": "2"
          }
        },
        {
          "@type": "AnnotationData",
          "@id": "6F19A8D4",
          "key": "root_idx_mapping",
          "value": {
            "@type": "String",
            "value": "3"
          }
        },
        {
          "@type": "AnnotationData",
          "@id": "F5637114",
          "key": "root_idx_mapping",
          "value": {
            "@type": "String",
            "value": "4"
          }
        },
        {
          "@type": "AnnotationData",
          "@id": "A75DAD87",
          "key": "root_idx_mapping",
          "value": {
            "@type": "String",
            "value": "5"
          }
        },
        {
          "@type": "AnnotationData",
          "@id": "32C9A917",
          "key": "root_idx_mapping",
          "value": {
            "@type": "String",
            "value": "6"
          }
        },
        {
          "@type": "AnnotationData",
          "@id": "FFE8FD33",
          "key": "root_idx_mapping",
          "value": {
            "@type": "String",
            "value": "7"
          }
        },
        {
          "@type": "AnnotationData",
          "@id": "AE5732A4",
          "key": "root_idx_mapping",
          "value": {
            "@type": "String",
            "value": "8"
          }
        },
        {
          "@type": "AnnotationData",
          "@id": "FEAFFD75",
          "key": "root_idx_mapping",
          "value": {
            "@type": "String",
            "value": "9"
          }
        },
        {
          "@type": "AnnotationData",
          "@id": "CF58DA8F",
          "key": "root_idx_mapping",
          "value": {
            "@type": "String",
            "value": "10"
          }
        },
        {
          "@type": "AnnotationData",
          "@id": "B0D349C4",
          "key": "root_idx_mapping",
          "value": {
            "@type": "String",
            "value": "11"
          }
        },
        {
          "@type": "AnnotationData",
          "@id": "B97D77DA",
          "key": "root_idx_mapping",
          "value": {
            "@type": "String",
            "value": "12"
          }
        },
        {
          "@type": "AnnotationData",
          "@id": "107EED31",
          "key": "root_idx_mapping",
          "value": {
            "@type": "String",
            "value": "13"
          }
        },
        {
          "@type": "AnnotationData",
          "@id": "3E43F7BF",
          "key": "root_idx_mapping",
          "value": {
            "@type": "String",
            "value": "14"
          }
        },
        {
          "@type": "AnnotationData",
          "@id": "65EEE636",
          "key": "root_idx_mapping",
          "value": {
            "@type": "String",
            "value": "15"
          }
        },
        {
          "@type": "AnnotationData",
          "@id": "1ABB2F18",
          "key": "root_idx_mapping",
          "value": {
            "@type": "String",
            "value": "16"
          }
        },
        {
          "@type": "AnnotationData",
          "@id": "3190F862",
          "key": "root_idx_mapping",
          "value": {
            "@type": "String",
            "value": "17"
          }
        },
        {
          "@type": "AnnotationData",
          "@id": "A5E6AB83",
          "key": "root_idx_mapping",
          "value": {
            "@type": "String",
            "value": "18"
          }
        },
        {
          "@type": "AnnotationData",
          "@id": "7EE121AE",
          "key": "root_idx_mapping",
          "value": {
            "@type": "String",
            "value": "19"
          }
        },
        {
          "@type": "AnnotationData",
          "@id": "FFF7F919",
          "key": "root_idx_mapping",
          "value": {
            "@type": "String",
            "value": "20"
          }
        },
        {
          "@type": "AnnotationData",
          "@id": "629B34E4",
          "key": "root_idx_mapping",
          "value": {
            "@type": "String",
            "value": "21"
          }
        },
        {
          "@type": "AnnotationData",
          "@id": "E6CB9936",
          "key": "root_idx_mapping",
          "value": {
            "@type": "String",
            "value": "22"
          }
        },
        {
          "@type": "AnnotationData",
          "@id": "F6079993",
          "key": "root_idx_mapping",
          "value": {
            "@type": "String",
            "value": "23"
          }
        },
        {
          "@type": "AnnotationData",
          "@id": "6FB0E865",
          "key": "root_idx_mapping",
          "value": {
            "@type": "String",
            "value": "24"
          }
        },
        {
          "@type": "AnnotationData",
          "@id": "04892946",
          "key": "root_idx_mapping",
          "value": {
            "@type": "String",
            "value": "25"
          }
        },
        {
          "@type": "AnnotationData",
          "@id": "346FE4C7",
          "key": "root_idx_mapping",
          "value": {
            "@type": "String",
            "value": "26"
          }
        },
        {
          "@type": "AnnotationData",
          "@id": "1A428CB2",
          "key": "root_idx_mapping",
          "value": {
            "@type": "String",
            "value": "27"
          }
        },
        {
          "@type": "AnnotationData",
          "@id": "15188E85",
          "key": "root_idx_mapping",
          "value": {
            "@type": "String",
            "value": "28"
          }
        },
        {
          "@type": "AnnotationData",
          "@id": "D3DA24A5",
          "key": "root_idx_mapping",
          "value": {
            "@type": "String",
            "value": "29"
          }
        },
        {
          "@type": "AnnotationData",
          "@id": "B9943B92",
          "key": "root_idx_mapping",
          "value": {
            "@type": "String",
            "value": "30"
          }
        },
        {
          "@type": "AnnotationData",
          "@id": "C0D5E5EA",
          "key": "root_idx_mapping",
          "value": {
            "@type": "String",
            "value": "31"
          }
        },
        {
          "@type": "AnnotationData",
          "@id": "86FB77B9",
          "key": "root_idx_mapping",
          "value": {
            "@type": "String",
            "value": "32"
          }
        },
        {
          "@type": "AnnotationData",
          "@id": "C37758B5",
          "key": "root_idx_mapping",
          "value": {
            "@type": "String",
            "value": "33"
          }
        },
        {
          "@type": "AnnotationData",
          "@id": "ABD2CCB3",
          "key": "root_idx_mapping",
          "value": {
            "@type": "String",
            "value": "34"
          }
        },
        {
          "@type": "AnnotationData",
          "@id": "3A48E6AA",
          "key": "root_idx_mapping",
          "value": {
            "@type": "String",
            "value": "35"
          }
        },
        {
          "@type": "AnnotationData",
          "@id": "00344FDF",
          "key": "root_idx_mapping",
          "value": {
            "@type": "String",
            "value": "36"
          }
        },
        {
          "@type": "AnnotationData",
          "@id": "6A3C0256",
          "key": "root_idx_mapping",
          "value": {
            "@type": "String",
            "value": "37"
          }
        },
        {
          "@type": "AnnotationData",
          "@id": "5546646D",
          "key": "root_idx_mapping",
          "value": {
            "@type": "String",
            "value": "38"
          }
        },
        {
          "@type": "AnnotationData",
          "@id": "06490D48",
          "key": "root_idx_mapping",
          "value": {
            "@type": "String",
            "value": "39"
          }
        },
        {
          "@type": "AnnotationData",
          "@id": "D34513FE",
          "key": "root_idx_mapping",
          "value": {
            "@type": "String",
            "value": "40"
          }
        },
        {
          "@type": "AnnotationData",
          "@id": "2C8FB8BF",
          "key": "root_idx_mapping",
          "value": {
            "@type": "String",
            "value": "41"
          }
        },
        {
          "@type": "AnnotationData",
          "@id": "D1FABA68",
          "key": "root_idx_mapping",
          "value": {
            "@type": "String",
            "value": "42"
          }
        },
        {
          "@type": "AnnotationData",
          "@id": "62C5BC82",
          "key": "root_idx_mapping",
          "value": {
            "@type": "String",
            "value": "43"
          }
        },
        {
          "@type": "AnnotationData",
          "@id": "3022EF82",
          "key": "root_idx_mapping",
          "value": {
            "@type": "String",
            "value": "44"
          }
        },
        {
          "@type": "AnnotationData",
          "@id": "3B08B7A1",
          "key": "root_idx_mapping",
          "value": {
            "@type": "String",
            "value": "45"
          }
        },
        {
          "@type": "AnnotationData",
          "@id": "9C954255",
          "key": "root_idx_mapping",
          "value": {
            "@type": "String",
            "value": "46"
          }
        },
        {
          "@type": "AnnotationData",
          "@id": "BAD4A144",
          "key": "root_idx_mapping",
          "value": {
            "@type": "String",
            "value": "47"
          }
        },
        {
          "@type": "AnnotationData",
          "@id": "E1C7354C",
          "key": "root_idx_mapping",
          "value": {
            "@type": "String",
            "value": "48"
          }
        },
        {
          "@type": "AnnotationData",
          "@id": "77488846",
          "key": "root_idx_mapping",
          "value": {
            "@type": "String",
            "value": "49"
          }
        },
        {
          "@type": "AnnotationData",
          "@id": "2E5B83B4",
          "key": "root_idx_mapping",
          "value": {
            "@type": "String",
            "value": "50"
          }
        },
        {
          "@type": "AnnotationData",
          "@id": "FE259AEF",
          "key": "root_idx_mapping",
          "value": {
            "@type": "String",
            "value": "51"
          }
        },
        {
          "@type": "AnnotationData",
          "@id": "BFEF6133",
          "key": "root_idx_mapping",
          "value": {
            "@type": "String",
            "value": "52"
          }
        },
        {
          "@type": "AnnotationData",
          "@id": "BCC18980",
          "key": "root_idx_mapping",
          "value": {
            "@type": "String",
            "value": "53"
          }
        },
        {
          "@type": "AnnotationData",
          "@id": "944093A7",
          "key": "root_idx_mapping",
          "value": {
            "@type": "String",
            "value": "54"
          }
        },
        {
          "@type": "AnnotationData",
          "@id": "CFA42AFF",
          "key": "root_idx_mapping",
          "value": {
            "@type": "String",
            "value": "55"
          }
        },
        {
          "@type": "AnnotationData",
          "@id": "AAC69909",
          "key": "root_idx_mapping",
          "value": {
            "@type": "String",
            "value": "56"
          }
        },
        {
          "@type": "AnnotationData",
          "@id": "4BB0B0D0",
          "key": "root_idx_mapping",
          "value": {
            "@type": "String",
            "value": "57"
          }
        },
        {
          "@type": "AnnotationData",
          "@id": "2268C68C",
          "key": "root_idx_mapping",
          "value": {
            "@type": "String",
            "value": "58"
          }
        },
        {
          "@type": "AnnotationData",
          "@id": "35CEE478",
          "key": "root_idx_mapping",
          "value": {
            "@type": "String",
            "value": "59"
          }
        },
        {
          "@type": "AnnotationData",
          "@id": "4BB26E08",
          "key": "root_idx_mapping",
          "value": {
            "@type": "String",
            "value": "60"
          }
        },
        {
          "@type": "AnnotationData",
          "@id": "E7BE489A",
          "key": "root_idx_mapping",
          "value": {
            "@type": "String",
            "value": "61"
          }
        },
        {
          "@type": "AnnotationData",
          "@id": "47ED4703",
          "key": "root_idx_mapping",
          "value": {
            "@type": "String",
            "value": "62"
          }
        },
        {
          "@type": "AnnotationData",
          "@id": "CD32A4C0",
          "key": "root_idx_mapping",
          "value": {
            "@type": "String",
            "value": "63"
          }
        },
        {
          "@type": "AnnotationData",
          "@id": "2520EC04",
          "key": "root_idx_mapping",
          "value": {
            "@type": "String",
            "value": "64"
          }
        }
      ]
    }
  ],
  "annotations": [
    {
      "@type": "Annotation",
      "@id": "83F3AAAF",
      "target": {
        "@type": "TextSelector",
        "resource": "DB0D",
        "offset": {
          "@type": "Offset",
          "begin": {
            "@type": "BeginAlignedCursor",
            "value": 0
          },
          "end": {
            "@type": "BeginAlignedCursor",
            "value": 71
          }
        }
      },
      "data": [
        {
          "@type": "AnnotationData",
          "@id": "CC2C2357",
          "set": "Translation"
        },
        {
          "@type": "AnnotationData",
          "@id": "F5A84DFB",
          "set": "Translation"
        }
      ]
    },
    {
      "@type": "Annotation",
      "@id": "C35D7891",
      "target": {
        "@type": "TextSelector",
        "resource": "DB0D",
        "offset": {
          "@type": "Offset",
          "begin": {
            "@type": "BeginAlignedCursor",
            "value": 71
          },
          "end": {
            "@type": "BeginAlignedCursor",
            "value": 267
          }
        }
      },
      "data": [
        {
          "@type": "AnnotationData",
          "@id": "6F83194C",
          "set": "Translation"
        },
        {
          "@type": "AnnotationData",
          "@id": "F5A84DFB",
          "set": "Translation"
        }
      ]
    },
    {
      "@type": "Annotation",
      "@id": "CA4390AB",
      "target": {
        "@type": "TextSelector",
        "resource": "DB0D",
        "offset": {
          "@type": "Offset",
          "begin": {
            "@type": "BeginAlignedCursor",
            "value": 267
          },
          "end": {
            "@type": "BeginAlignedCursor",
            "value": 480
          }
        }
      },
      "data": [
        {
          "@type": "AnnotationData",
          "@id": "6F19A8D4",
          "set": "Translation"
        },
        {
          "@type": "AnnotationData",
          "@id": "F5A84DFB",
          "set": "Translation"
        }
      ]
    },
    {
      "@type": "Annotation",
      "@id": "F79C6EA0",
      "target": {
        "@type": "TextSelector",
        "resource": "DB0D",
        "offset": {
          "@type": "Offset",
          "begin": {
            "@type": "BeginAlignedCursor",
            "value": 480
          },
          "end": {
            "@type": "BeginAlignedCursor",
            "value": 676
          }
        }
      },
      "data": [
        {
          "@type": "AnnotationData",
          "@id": "F5637114",
          "set": "Translation"
        },
        {
          "@type": "AnnotationData",
          "@id": "F5A84DFB",
          "set": "Translation"
        }
      ]
    },
    {
      "@type": "Annotation",
      "@id": "AF9A5440",
      "target": {
        "@type": "TextSelector",
        "resource": "DB0D",
        "offset": {
          "@type": "Offset",
          "begin": {
            "@type": "BeginAlignedCursor",
            "value": 676
          },
          "end": {
            "@type": "BeginAlignedCursor",
            "value": 868
          }
        }
      },
      "data": [
        {
          "@type": "AnnotationData",
          "@id": "A75DAD87",
          "set": "Translation"
        },
        {
          "@type": "AnnotationData",
          "@id": "F5A84DFB",
          "set": "Translation"
        }
      ]
    },
    {
      "@type": "Annotation",
      "@id": "87F3A363",
      "target": {
        "@type": "TextSelector",
        "resource": "DB0D",
        "offset": {
          "@type": "Offset",
          "begin": {
            "@type": "BeginAlignedCursor",
            "value": 868
          },
          "end": {
            "@type": "BeginAlignedCursor",
            "value": 1071
          }
        }
      },
      "data": [
        {
          "@type": "AnnotationData",
          "@id": "32C9A917",
          "set": "Translation"
        },
        {
          "@type": "AnnotationData",
          "@id": "F5A84DFB",
          "set": "Translation"
        }
      ]
    },
    {
      "@type": "Annotation",
      "@id": "B59994C2",
      "target": {
        "@type": "TextSelector",
        "resource": "DB0D",
        "offset": {
          "@type": "Offset",
          "begin": {
            "@type": "BeginAlignedCursor",
            "value": 1071
          },
          "end": {
            "@type": "BeginAlignedCursor",
            "value": 1254
          }
        }
      },
      "data": [
        {
          "@type": "AnnotationData",
          "@id": "FFE8FD33",
          "set": "Translation"
        },
        {
          "@type": "AnnotationData",
          "@id": "F5A84DFB",
          "set": "Translation"
        }
      ]
    },
    {
      "@type": "Annotation",
      "@id": "437AC177",
      "target": {
        "@type": "TextSelector",
        "resource": "DB0D",
        "offset": {
          "@type": "Offset",
          "begin": {
            "@type": "BeginAlignedCursor",
            "value": 1254
          },
          "end": {
            "@type": "BeginAlignedCursor",
            "value": 1447
          }
        }
      },
      "data": [
        {
          "@type": "AnnotationData",
          "@id": "AE5732A4",
          "set": "Translation"
        },
        {
          "@type": "AnnotationData",
          "@id": "F5A84DFB",
          "set": "Translation"
        }
      ]
    },
    {
      "@type": "Annotation",
      "@id": "E4D44551",
      "target": {
        "@type": "TextSelector",
        "resource": "DB0D",
        "offset": {
          "@type": "Offset",
          "begin": {
            "@type": "BeginAlignedCursor",
            "value": 1447
          },
          "end": {
            "@type": "BeginAlignedCursor",
            "value": 1661
          }
        }
      },
      "data": [
        {
          "@type": "AnnotationData",
          "@id": "FEAFFD75",
          "set": "Translation"
        },
        {
          "@type": "AnnotationData",
          "@id": "F5A84DFB",
          "set": "Translation"
        }
      ]
    },
    {
      "@type": "Annotation",
      "@id": "0220E02A",
      "target": {
        "@type": "TextSelector",
        "resource": "DB0D",
        "offset": {
          "@type": "Offset",
          "begin": {
            "@type": "BeginAlignedCursor",
            "value": 1661
          },
          "end": {
            "@type": "BeginAlignedCursor",
            "value": 1870
          }
        }
      },
      "data": [
        {
          "@type": "AnnotationData",
          "@id": "CF58DA8F",
          "set": "Translation"
        },
        {
          "@type": "AnnotationData",
          "@id": "F5A84DFB",
          "set": "Translation"
        }
      ]
    },
    {
      "@type": "Annotation",
      "@id": "46FFF632",
      "target": {
        "@type": "TextSelector",
        "resource": "DB0D",
        "offset": {
          "@type": "Offset",
          "begin": {
            "@type": "BeginAlignedCursor",
            "value": 1870
          },
          "end": {
            "@type": "BeginAlignedCursor",
            "value": 2095
          }
        }
      },
      "data": [
        {
          "@type": "AnnotationData",
          "@id": "B0D349C4",
          "set": "Translation"
        },
        {
          "@type": "AnnotationData",
          "@id": "F5A84DFB",
          "set": "Translation"
        }
      ]
    },
    {
      "@type": "Annotation",
      "@id": "944DE5BB",
      "target": {
        "@type": "TextSelector",
        "resource": "DB0D",
        "offset": {
          "@type": "Offset",
          "begin": {
            "@type": "BeginAlignedCursor",
            "value": 2095
          },
          "end": {
            "@type": "BeginAlignedCursor",
            "value": 2335
          }
        }
      },
      "data": [
        {
          "@type": "AnnotationData",
          "@id": "B97D77DA",
          "set": "Translation"
        },
        {
          "@type": "AnnotationData",
          "@id": "F5A84DFB",
          "set": "Translation"
        }
      ]
    },
    {
      "@type": "Annotation",
      "@id": "7559A748",
      "target": {
        "@type": "TextSelector",
        "resource": "DB0D",
        "offset": {
          "@type": "Offset",
          "begin": {
            "@type": "BeginAlignedCursor",
            "value": 2335
          },
          "end": {
            "@type": "BeginAlignedCursor",
            "value": 2632
          }
        }
      },
      "data": [
        {
          "@type": "AnnotationData",
          "@id": "107EED31",
          "set": "Translation"
        },
        {
          "@type": "AnnotationData",
          "@id": "F5A84DFB",
          "set": "Translation"
        }
      ]
    },
    {
      "@type": "Annotation",
      "@id": "BB4337F4",
      "target": {
        "@type": "TextSelector",
        "resource": "DB0D",
        "offset": {
          "@type": "Offset",
          "begin": {
            "@type": "BeginAlignedCursor",
            "value": 2632
          },
          "end": {
            "@type": "BeginAlignedCursor",
            "value": 2901
          }
        }
      },
      "data": [
        {
          "@type": "AnnotationData",
          "@id": "3E43F7BF",
          "set": "Translation"
        },
        {
          "@type": "AnnotationData",
          "@id": "F5A84DFB",
          "set": "Translation"
        }
      ]
    },
    {
      "@type": "Annotation",
      "@id": "8188EF28",
      "target": {
        "@type": "TextSelector",
        "resource": "DB0D",
        "offset": {
          "@type": "Offset",
          "begin": {
            "@type": "BeginAlignedCursor",
            "value": 2901
          },
          "end": {
            "@type": "BeginAlignedCursor",
            "value": 3130
          }
        }
      },
      "data": [
        {
          "@type": "AnnotationData",
          "@id": "65EEE636",
          "set": "Translation"
        },
        {
          "@type": "AnnotationData",
          "@id": "F5A84DFB",
          "set": "Translation"
        }
      ]
    },
    {
      "@type": "Annotation",
      "@id": "99001B93",
      "target": {
        "@type": "TextSelector",
        "resource": "DB0D",
        "offset": {
          "@type": "Offset",
          "begin": {
            "@type": "BeginAlignedCursor",
            "value": 3130
          },
          "end": {
            "@type": "BeginAlignedCursor",
            "value": 3403
          }
        }
      },
      "data": [
        {
          "@type": "AnnotationData",
          "@id": "1ABB2F18",
          "set": "Translation"
        },
        {
          "@type": "AnnotationData",
          "@id": "F5A84DFB",
          "set": "Translation"
        }
      ]
    },
    {
      "@type": "Annotation",
      "@id": "5746CB4A",
      "target": {
        "@type": "TextSelector",
        "resource": "DB0D",
        "offset": {
          "@type": "Offset",
          "begin": {
            "@type": "BeginAlignedCursor",
            "value": 3403
          },
          "end": {
            "@type": "BeginAlignedCursor",
            "value": 3606
          }
        }
      },
      "data": [
        {
          "@type": "AnnotationData",
          "@id": "3190F862",
          "set": "Translation"
        },
        {
          "@type": "AnnotationData",
          "@id": "F5A84DFB",
          "set": "Translation"
        }
      ]
    },
    {
      "@type": "Annotation",
      "@id": "4EE26684",
      "target": {
        "@type": "TextSelector",
        "resource": "DB0D",
        "offset": {
          "@type": "Offset",
          "begin": {
            "@type": "BeginAlignedCursor",
            "value": 3606
          },
          "end": {
            "@type": "BeginAlignedCursor",
            "value": 3851
          }
        }
      },
      "data": [
        {
          "@type": "AnnotationData",
          "@id": "A5E6AB83",
          "set": "Translation"
        },
        {
          "@type": "AnnotationData",
          "@id": "F5A84DFB",
          "set": "Translation"
        }
      ]
    },
    {
      "@type": "Annotation",
      "@id": "92DD4546",
      "target": {
        "@type": "TextSelector",
        "resource": "DB0D",
        "offset": {
          "@type": "Offset",
          "begin": {
            "@type": "BeginAlignedCursor",
            "value": 3851
          },
          "end": {
            "@type": "BeginAlignedCursor",
            "value": 4138
          }
        }
      },
      "data": [
        {
          "@type": "AnnotationData",
          "@id": "7EE121AE",
          "set": "Translation"
        },
        {
          "@type": "AnnotationData",
          "@id": "F5A84DFB",
          "set": "Translation"
        }
      ]
    },
    {
      "@type": "Annotation",
      "@id": "48B8E99F",
      "target": {
        "@type": "TextSelector",
        "resource": "DB0D",
        "offset": {
          "@type": "Offset",
          "begin": {
            "@type": "BeginAlignedCursor",
            "value": 4138
          },
          "end": {
            "@type": "BeginAlignedCursor",
            "value": 4399
          }
        }
      },
      "data": [
        {
          "@type": "AnnotationData",
          "@id": "FFF7F919",
          "set": "Translation"
        },
        {
          "@type": "AnnotationData",
          "@id": "F5A84DFB",
          "set": "Translation"
        }
      ]
    },
    {
      "@type": "Annotation",
      "@id": "E125E465",
      "target": {
        "@type": "TextSelector",
        "resource": "DB0D",
        "offset": {
          "@type": "Offset",
          "begin": {
            "@type": "BeginAlignedCursor",
            "value": 4399
          },
          "end": {
            "@type": "BeginAlignedCursor",
            "value": 4636
          }
        }
      },
      "data": [
        {
          "@type": "AnnotationData",
          "@id": "629B34E4",
          "set": "Translation"
        },
        {
          "@type": "AnnotationData",
          "@id": "F5A84DFB",
          "set": "Translation"
        }
      ]
    },
    {
      "@type": "Annotation",
      "@id": "3094AAA9",
      "target": {
        "@type": "TextSelector",
        "resource": "DB0D",
        "offset": {
          "@type": "Offset",
          "begin": {
            "@type": "BeginAlignedCursor",
            "value": 4636
          },
          "end": {
            "@type": "BeginAlignedCursor",
            "value": 4969
          }
        }
      },
      "data": [
        {
          "@type": "AnnotationData",
          "@id": "E6CB9936",
          "set": "Translation"
        },
        {
          "@type": "AnnotationData",
          "@id": "F5A84DFB",
          "set": "Translation"
        }
      ]
    },
    {
      "@type": "Annotation",
      "@id": "E4B30C01",
      "target": {
        "@type": "TextSelector",
        "resource": "DB0D",
        "offset": {
          "@type": "Offset",
          "begin": {
            "@type": "BeginAlignedCursor",
            "value": 4969
          },
          "end": {
            "@type": "BeginAlignedCursor",
            "value": 5211
          }
        }
      },
      "data": [
        {
          "@type": "AnnotationData",
          "@id": "F6079993",
          "set": "Translation"
        },
        {
          "@type": "AnnotationData",
          "@id": "F5A84DFB",
          "set": "Translation"
        }
      ]
    },
    {
      "@type": "Annotation",
      "@id": "994B6BF2",
      "target": {
        "@type": "TextSelector",
        "resource": "DB0D",
        "offset": {
          "@type": "Offset",
          "begin": {
            "@type": "BeginAlignedCursor",
            "value": 5211
          },
          "end": {
            "@type": "BeginAlignedCursor",
            "value": 5396
          }
        }
      },
      "data": [
        {
          "@type": "AnnotationData",
          "@id": "6FB0E865",
          "set": "Translation"
        },
        {
          "@type": "AnnotationData",
          "@id": "F5A84DFB",
          "set": "Translation"
        }
      ]
    },
    {
      "@type": "Annotation",
      "@id": "FF344220",
      "target": {
        "@type": "TextSelector",
        "resource": "DB0D",
        "offset": {
          "@type": "Offset",
          "begin": {
            "@type": "BeginAlignedCursor",
            "value": 5396
          },
          "end": {
            "@type": "BeginAlignedCursor",
            "value": 5602
          }
        }
      },
      "data": [
        {
          "@type": "AnnotationData",
          "@id": "04892946",
          "set": "Translation"
        },
        {
          "@type": "AnnotationData",
          "@id": "F5A84DFB",
          "set": "Translation"
        }
      ]
    },
    {
      "@type": "Annotation",
      "@id": "E0AA9884",
      "target": {
        "@type": "TextSelector",
        "resource": "DB0D",
        "offset": {
          "@type": "Offset",
          "begin": {
            "@type": "BeginAlignedCursor",
            "value": 5602
          },
          "end": {
            "@type": "BeginAlignedCursor",
            "value": 5750
          }
        }
      },
      "data": [
        {
          "@type": "AnnotationData",
          "@id": "346FE4C7",
          "set": "Translation"
        },
        {
          "@type": "AnnotationData",
          "@id": "F5A84DFB",
          "set": "Translation"
        }
      ]
    },
    {
      "@type": "Annotation",
      "@id": "1FF216A4",
      "target": {
        "@type": "TextSelector",
        "resource": "DB0D",
        "offset": {
          "@type": "Offset",
          "begin": {
            "@type": "BeginAlignedCursor",
            "value": 5750
          },
          "end": {
            "@type": "BeginAlignedCursor",
            "value": 5958
          }
        }
      },
      "data": [
        {
          "@type": "AnnotationData",
          "@id": "1A428CB2",
          "set": "Translation"
        },
        {
          "@type": "AnnotationData",
          "@id": "F5A84DFB",
          "set": "Translation"
        }
      ]
    },
    {
      "@type": "Annotation",
      "@id": "E59BACBF",
      "target": {
        "@type": "TextSelector",
        "resource": "DB0D",
        "offset": {
          "@type": "Offset",
          "begin": {
            "@type": "BeginAlignedCursor",
            "value": 5958
          },
          "end": {
            "@type": "BeginAlignedCursor",
            "value": 6145
          }
        }
      },
      "data": [
        {
          "@type": "AnnotationData",
          "@id": "15188E85",
          "set": "Translation"
        },
        {
          "@type": "AnnotationData",
          "@id": "F5A84DFB",
          "set": "Translation"
        }
      ]
    },
    {
      "@type": "Annotation",
      "@id": "6ADD529A",
      "target": {
        "@type": "TextSelector",
        "resource": "DB0D",
        "offset": {
          "@type": "Offset",
          "begin": {
            "@type": "BeginAlignedCursor",
            "value": 6145
          },
          "end": {
            "@type": "BeginAlignedCursor",
            "value": 6370
          }
        }
      },
      "data": [
        {
          "@type": "AnnotationData",
          "@id": "D3DA24A5",
          "set": "Translation"
        },
        {
          "@type": "AnnotationData",
          "@id": "F5A84DFB",
          "set": "Translation"
        }
      ]
    },
    {
      "@type": "Annotation",
      "@id": "DD2902E9",
      "target": {
        "@type": "TextSelector",
        "resource": "DB0D",
        "offset": {
          "@type": "Offset",
          "begin": {
            "@type": "BeginAlignedCursor",
            "value": 6370
          },
          "end": {
            "@type": "BeginAlignedCursor",
            "value": 6541
          }
        }
      },
      "data": [
        {
          "@type": "AnnotationData",
          "@id": "B9943B92",
          "set": "Translation"
        },
        {
          "@type": "AnnotationData",
          "@id": "F5A84DFB",
          "set": "Translation"
        }
      ]
    },
    {
      "@type": "Annotation",
      "@id": "3A2AF99A",
      "target": {
        "@type": "TextSelector",
        "resource": "DB0D",
        "offset": {
          "@type": "Offset",
          "begin": {
            "@type": "BeginAlignedCursor",
            "value": 6541
          },
          "end": {
            "@type": "BeginAlignedCursor",
            "value": 6730
          }
        }
      },
      "data": [
        {
          "@type": "AnnotationData",
          "@id": "C0D5E5EA",
          "set": "Translation"
        },
        {
          "@type": "AnnotationData",
          "@id": "F5A84DFB",
          "set": "Translation"
        }
      ]
    },
    {
      "@type": "Annotation",
      "@id": "CC15EF0F",
      "target": {
        "@type": "TextSelector",
        "resource": "DB0D",
        "offset": {
          "@type": "Offset",
          "begin": {
            "@type": "BeginAlignedCursor",
            "value": 6730
          },
          "end": {
            "@type": "BeginAlignedCursor",
            "value": 6931
          }
        }
      },
      "data": [
        {
          "@type": "AnnotationData",
          "@id": "86FB77B9",
          "set": "Translation"
        },
        {
          "@type": "AnnotationData",
          "@id": "F5A84DFB",
          "set": "Translation"
        }
      ]
    },
    {
      "@type": "Annotation",
      "@id": "124D28E4",
      "target": {
        "@type": "TextSelector",
        "resource": "DB0D",
        "offset": {
          "@type": "Offset",
          "begin": {
            "@type": "BeginAlignedCursor",
            "value": 6931
          },
          "end": {
            "@type": "BeginAlignedCursor",
            "value": 7115
          }
        }
      },
      "data": [
        {
          "@type": "AnnotationData",
          "@id": "C37758B5",
          "set": "Translation"
        },
        {
          "@type": "AnnotationData",
          "@id": "F5A84DFB",
          "set": "Translation"
        }
      ]
    },
    {
      "@type": "Annotation",
      "@id": "D431C300",
      "target": {
        "@type": "TextSelector",
        "resource": "DB0D",
        "offset": {
          "@type": "Offset",
          "begin": {
            "@type": "BeginAlignedCursor",
            "value": 7115
          },
          "end": {
            "@type": "BeginAlignedCursor",
            "value": 7303
          }
        }
      },
      "data": [
        {
          "@type": "AnnotationData",
          "@id": "ABD2CCB3",
          "set": "Translation"
        },
        {
          "@type": "AnnotationData",
          "@id": "F5A84DFB",
          "set": "Translation"
        }
      ]
    },
    {
      "@type": "Annotation",
      "@id": "256F3A34",
      "target": {
        "@type": "TextSelector",
        "resource": "DB0D",
        "offset": {
          "@type": "Offset",
          "begin": {
            "@type": "BeginAlignedCursor",
            "value": 7303
          },
          "end": {
            "@type": "BeginAlignedCursor",
            "value": 7495
          }
        }
      },
      "data": [
        {
          "@type": "AnnotationData",
          "@id": "3A48E6AA",
          "set": "Translation"
        },
        {
          "@type": "AnnotationData",
          "@id": "F5A84DFB",
          "set": "Translation"
        }
      ]
    },
    {
      "@type": "Annotation",
      "@id": "D426703E",
      "target": {
        "@type": "TextSelector",
        "resource": "DB0D",
        "offset": {
          "@type": "Offset",
          "begin": {
            "@type": "BeginAlignedCursor",
            "value": 7495
          },
          "end": {
            "@type": "BeginAlignedCursor",
            "value": 7677
          }
        }
      },
      "data": [
        {
          "@type": "AnnotationData",
          "@id": "00344FDF",
          "set": "Translation"
        },
        {
          "@type": "AnnotationData",
          "@id": "F5A84DFB",
          "set": "Translation"
        }
      ]
    },
    {
      "@type": "Annotation",
      "@id": "B25595D1",
      "target": {
        "@type": "TextSelector",
        "resource": "DB0D",
        "offset": {
          "@type": "Offset",
          "begin": {
            "@type": "BeginAlignedCursor",
            "value": 7677
          },
          "end": {
            "@type": "BeginAlignedCursor",
            "value": 7917
          }
        }
      },
      "data": [
        {
          "@type": "AnnotationData",
          "@id": "6A3C0256",
          "set": "Translation"
        },
        {
          "@type": "AnnotationData",
          "@id": "F5A84DFB",
          "set": "Translation"
        }
      ]
    },
    {
      "@type": "Annotation",
      "@id": "7EADE2A2",
      "target": {
        "@type": "TextSelector",
        "resource": "DB0D",
        "offset": {
          "@type": "Offset",
          "begin": {
            "@type": "BeginAlignedCursor",
            "value": 7917
          },
          "end": {
            "@type": "BeginAlignedCursor",
            "value": 8086
          }
        }
      },
      "data": [
        {
          "@type": "AnnotationData",
          "@id": "5546646D",
          "set": "Translation"
        },
        {
          "@type": "AnnotationData",
          "@id": "F5A84DFB",
          "set": "Translation"
        }
      ]
    },
    {
      "@type": "Annotation",
      "@id": "E477EC42",
      "target": {
        "@type": "TextSelector",
        "resource": "DB0D",
        "offset": {
          "@type": "Offset",
          "begin": {
            "@type": "BeginAlignedCursor",
            "value": 8086
          },
          "end": {
            "@type": "BeginAlignedCursor",
            "value": 8247
          }
        }
      },
      "data": [
        {
          "@type": "AnnotationData",
          "@id": "06490D48",
          "set": "Translation"
        },
        {
          "@type": "AnnotationData",
          "@id": "F5A84DFB",
          "set": "Translation"
        }
      ]
    },
    {
      "@type": "Annotation",
      "@id": "751563FF",
      "target": {
        "@type": "TextSelector",
        "resource": "DB0D",
        "offset": {
          "@type": "Offset",
          "begin": {
            "@type": "BeginAlignedCursor",
            "value": 8247
          },
          "end": {
            "@type": "BeginAlignedCursor",
            "value": 8425
          }
        }
      },
      "data": [
        {
          "@type": "AnnotationData",
          "@id": "D34513FE",
          "set": "Translation"
        },
        {
          "@type": "AnnotationData",
          "@id": "F5A84DFB",
          "set": "Translation"
        }
      ]
    },
    {
      "@type": "Annotation",
      "@id": "0BC23B93",
      "target": {
        "@type": "TextSelector",
        "resource": "DB0D",
        "offset": {
          "@type": "Offset",
          "begin": {
            "@type": "BeginAlignedCursor",
            "value": 8425
          },
          "end": {
            "@type": "BeginAlignedCursor",
            "value": 8615
          }
        }
      },
      "data": [
        {
          "@type": "AnnotationData",
          "@id": "2C8FB8BF",
          "set": "Translation"
        },
        {
          "@type": "AnnotationData",
          "@id": "F5A84DFB",
          "set": "Translation"
        }
      ]
    },
    {
      "@type": "Annotation",
      "@id": "B35DD335",
      "target": {
        "@type": "TextSelector",
        "resource": "DB0D",
        "offset": {
          "@type": "Offset",
          "begin": {
            "@type": "BeginAlignedCursor",
            "value": 8615
          },
          "end": {
            "@type": "BeginAlignedCursor",
            "value": 8825
          }
        }
      },
      "data": [
        {
          "@type": "AnnotationData",
          "@id": "D1FABA68",
          "set": "Translation"
        },
        {
          "@type": "AnnotationData",
          "@id": "F5A84DFB",
          "set": "Translation"
        }
      ]
    },
    {
      "@type": "Annotation",
      "@id": "8A3D7E3D",
      "target": {
        "@type": "TextSelector",
        "resource": "DB0D",
        "offset": {
          "@type": "Offset",
          "begin": {
            "@type": "BeginAlignedCursor",
            "value": 8825
          },
          "end": {
            "@type": "BeginAlignedCursor",
            "value": 9025
          }
        }
      },
      "data": [
        {
          "@type": "AnnotationData",
          "@id": "62C5BC82",
          "set": "Translation"
        },
        {
          "@type": "AnnotationData",
          "@id": "F5A84DFB",
          "set": "Translation"
        }
      ]
    },
    {
      "@type": "Annotation",
      "@id": "49C7AC4E",
      "target": {
        "@type": "TextSelector",
        "resource": "DB0D",
        "offset": {
          "@type": "Offset",
          "begin": {
            "@type": "BeginAlignedCursor",
            "value": 9025
          },
          "end": {
            "@type": "BeginAlignedCursor",
            "value": 9222
          }
        }
      },
      "data": [
        {
          "@type": "AnnotationData",
          "@id": "3022EF82",
          "set": "Translation"
        },
        {
          "@type": "AnnotationData",
          "@id": "F5A84DFB",
          "set": "Translation"
        }
      ]
    },
    {
      "@type": "Annotation",
      "@id": "BF80FA8E",
      "target": {
        "@type": "TextSelector",
        "resource": "DB0D",
        "offset": {
          "@type": "Offset",
          "begin": {
            "@type": "BeginAlignedCursor",
            "value": 9222
          },
          "end": {
            "@type": "BeginAlignedCursor",
            "value": 9419
          }
        }
      },
      "data": [
        {
          "@type": "AnnotationData",
          "@id": "3B08B7A1",
          "set": "Translation"
        },
        {
          "@type": "AnnotationData",
          "@id": "F5A84DFB",
          "set": "Translation"
        }
      ]
    },
    {
      "@type": "Annotation",
      "@id": "2D2C75DB",
      "target": {
        "@type": "TextSelector",
        "resource": "DB0D",
        "offset": {
          "@type": "Offset",
          "begin": {
            "@type": "BeginAlignedCursor",
            "value": 9419
          },
          "end": {
            "@type": "BeginAlignedCursor",
            "value": 9608
          }
        }
      },
      "data": [
        {
          "@type": "AnnotationData",
          "@id": "9C954255",
          "set": "Translation"
        },
        {
          "@type": "AnnotationData",
          "@id": "F5A84DFB",
          "set": "Translation"
        }
      ]
    },
    {
      "@type": "Annotation",
      "@id": "4E7B0277",
      "target": {
        "@type": "TextSelector",
        "resource": "DB0D",
        "offset": {
          "@type": "Offset",
          "begin": {
            "@type": "BeginAlignedCursor",
            "value": 9608
          },
          "end": {
            "@type": "BeginAlignedCursor",
            "value": 9770
          }
        }
      },
      "data": [
        {
          "@type": "AnnotationData",
          "@id": "BAD4A144",
          "set": "Translation"
        },
        {
          "@type": "AnnotationData",
          "@id": "F5A84DFB",
          "set": "Translation"
        }
      ]
    },
    {
      "@type": "Annotation",
      "@id": "944F9834",
      "target": {
        "@type": "TextSelector",
        "resource": "DB0D",
        "offset": {
          "@type": "Offset",
          "begin": {
            "@type": "BeginAlignedCursor",
            "value": 9770
          },
          "end": {
            "@type": "BeginAlignedCursor",
            "value": 9942
          }
        }
      },
      "data": [
        {
          "@type": "AnnotationData",
          "@id": "E1C7354C",
          "set": "Translation"
        },
        {
          "@type": "AnnotationData",
          "@id": "F5A84DFB",
          "set": "Translation"
        }
      ]
    },
    {
      "@type": "Annotation",
      "@id": "CBA83A54",
      "target": {
        "@type": "TextSelector",
        "resource": "DB0D",
        "offset": {
          "@type": "Offset",
          "begin": {
            "@type": "BeginAlignedCursor",
            "value": 9942
          },
          "end": {
            "@type": "BeginAlignedCursor",
            "value": 10118
          }
        }
      },
      "data": [
        {
          "@type": "AnnotationData",
          "@id": "77488846",
          "set": "Translation"
        },
        {
          "@type": "AnnotationData",
          "@id": "F5A84DFB",
          "set": "Translation"
        }
      ]
    },
    {
      "@type": "Annotation",
      "@id": "46BB64C9",
      "target": {
        "@type": "TextSelector",
        "resource": "DB0D",
        "offset": {
          "@type": "Offset",
          "begin": {
            "@type": "BeginAlignedCursor",
            "value": 10118
          },
          "end": {
            "@type": "BeginAlignedCursor",
            "value": 10341
          }
        }
      },
      "data": [
        {
          "@type": "AnnotationData",
          "@id": "2E5B83B4",
          "set": "Translation"
        },
        {
          "@type": "AnnotationData",
          "@id": "F5A84DFB",
          "set": "Translation"
        }
      ]
    },
    {
      "@type": "Annotation",
      "@id": "7A61376F",
      "target": {
        "@type": "TextSelector",
        "resource": "DB0D",
        "offset": {
          "@type": "Offset",
          "begin": {
            "@type": "BeginAlignedCursor",
            "value": 10341
          },
          "end": {
            "@type": "BeginAlignedCursor",
            "value": 10536
          }
        }
      },
      "data": [
        {
          "@type": "AnnotationData",
          "@id": "FE259AEF",
          "set": "Translation"
        },
        {
          "@type": "AnnotationData",
          "@id": "F5A84DFB",
          "set": "Translation"
        }
      ]
    },
    {
      "@type": "Annotation",
      "@id": "44F42E3C",
      "target": {
        "@type": "TextSelector",
        "resource": "DB0D",
        "offset": {
          "@type": "Offset",
          "begin": {
            "@type": "BeginAlignedCursor",
            "value": 10536
          },
          "end": {
            "@type": "BeginAlignedCursor",
            "value": 10718
          }
        }
      },
      "data": [
        {
          "@type": "AnnotationData",
          "@id": "BFEF6133",
          "set": "Translation"
        },
        {
          "@type": "AnnotationData",
          "@id": "F5A84DFB",
          "set": "Translation"
        }
      ]
    },
    {
      "@type": "Annotation",
      "@id": "1CCA4F78",
      "target": {
        "@type": "TextSelector",
        "resource": "DB0D",
        "offset": {
          "@type": "Offset",
          "begin": {
            "@type": "BeginAlignedCursor",
            "value": 10718
          },
          "end": {
            "@type": "BeginAlignedCursor",
            "value": 10907
          }
        }
      },
      "data": [
        {
          "@type": "AnnotationData",
          "@id": "BCC18980",
          "set": "Translation"
        },
        {
          "@type": "AnnotationData",
          "@id": "F5A84DFB",
          "set": "Translation"
        }
      ]
    },
    {
      "@type": "Annotation",
      "@id": "8BC47B13",
      "target": {
        "@type": "TextSelector",
        "resource": "DB0D",
        "offset": {
          "@type": "Offset",
          "begin": {
            "@type": "BeginAlignedCursor",
            "value": 10907
          },
          "end": {
            "@type": "BeginAlignedCursor",
            "value": 11113
          }
        }
      },
      "data": [
        {
          "@type": "AnnotationData",
          "@id": "944093A7",
          "set": "Translation"
        },
        {
          "@type": "AnnotationData",
          "@id": "F5A84DFB",
          "set": "Translation"
        }
      ]
    },
    {
      "@type": "Annotation",
      "@id": "AAF91CA1",
      "target": {
        "@type": "TextSelector",
        "resource": "DB0D",
        "offset": {
          "@type": "Offset",
          "begin": {
            "@type": "BeginAlignedCursor",
            "value": 11113
          },
          "end": {
            "@type": "BeginAlignedCursor",
            "value": 11334
          }
        }
      },
      "data": [
        {
          "@type": "AnnotationData",
          "@id": "CFA42AFF",
          "set": "Translation"
        },
        {
          "@type": "AnnotationData",
          "@id": "F5A84DFB",
          "set": "Translation"
        }
      ]
    },
    {
      "@type": "Annotation",
      "@id": "655D35D6",
      "target": {
        "@type": "TextSelector",
        "resource": "DB0D",
        "offset": {
          "@type": "Offset",
          "begin": {
            "@type": "BeginAlignedCursor",
            "value": 11334
          },
          "end": {
            "@type": "BeginAlignedCursor",
            "value": 11578
          }
        }
      },
      "data": [
        {
          "@type": "AnnotationData",
          "@id": "AAC69909",
          "set": "Translation"
        },
        {
          "@type": "AnnotationData",
          "@id": "F5A84DFB",
          "set": "Translation"
        }
      ]
    },
    {
      "@type": "Annotation",
      "@id": "5142720F",
      "target": {
        "@type": "TextSelector",
        "resource": "DB0D",
        "offset": {
          "@type": "Offset",
          "begin": {
            "@type": "BeginAlignedCursor",
            "value": 11578
          },
          "end": {
            "@type": "BeginAlignedCursor",
            "value": 11840
          }
        }
      },
      "data": [
        {
          "@type": "AnnotationData",
          "@id": "4BB0B0D0",
          "set": "Translation"
        },
        {
          "@type": "AnnotationData",
          "@id": "F5A84DFB",
          "set": "Translation"
        }
      ]
    },
    {
      "@type": "Annotation",
      "@id": "3EB813FF",
      "target": {
        "@type": "TextSelector",
        "resource": "DB0D",
        "offset": {
          "@type": "Offset",
          "begin": {
            "@type": "BeginAlignedCursor",
            "value": 11840
          },
          "end": {
            "@type": "BeginAlignedCursor",
            "value": 12028
          }
        }
      },
      "data": [
        {
          "@type": "AnnotationData",
          "@id": "2268C68C",
          "set": "Translation"
        },
        {
          "@type": "AnnotationData",
          "@id": "F5A84DFB",
          "set": "Translation"
        }
      ]
    },
    {
      "@type": "Annotation",
      "@id": "5422B505",
      "target": {
        "@type": "TextSelector",
        "resource": "DB0D",
        "offset": {
          "@type": "Offset",
          "begin": {
            "@type": "BeginAlignedCursor",
            "value": 12028
          },
          "end": {
            "@type": "BeginAlignedCursor",
            "value": 12230
          }
        }
      },
      "data": [
        {
          "@type": "AnnotationData",
          "@id": "35CEE478",
          "set": "Translation"
        },
        {
          "@type": "AnnotationData",
          "@id": "F5A84DFB",
          "set": "Translation"
        }
      ]
    },
    {
      "@type": "Annotation",
      "@id": "8ED222D9",
      "target": {
        "@type": "TextSelector",
        "resource": "DB0D",
        "offset": {
          "@type": "Offset",
          "begin": {
            "@type": "BeginAlignedCursor",
            "value": 12230
          },
          "end": {
            "@type": "BeginAlignedCursor",
            "value": 12391
          }
        }
      },
      "data": [
        {
          "@type": "AnnotationData",
          "@id": "4BB26E08",
          "set": "Translation"
        },
        {
          "@type": "AnnotationData",
          "@id": "F5A84DFB",
          "set": "Translation"
        }
      ]
    },
    {
      "@type": "Annotation",
      "@id": "C7ABBFFA",
      "target": {
        "@type": "TextSelector",
        "resource": "DB0D",
        "offset": {
          "@type": "Offset",
          "begin": {
            "@type": "BeginAlignedCursor",
            "value": 12391
          },
          "end": {
            "@type": "BeginAlignedCursor",
            "value": 12596
          }
        }
      },
      "data": [
        {
          "@type": "AnnotationData",
          "@id": "E7BE489A",
          "set": "Translation"
        },
        {
          "@type": "AnnotationData",
          "@id": "F5A84DFB",
          "set": "Translation"
        }
      ]
    },
    {
      "@type": "Annotation",
      "@id": "FC220ED1",
      "target": {
        "@type": "TextSelector",
        "resource": "DB0D",
        "offset": {
          "@type": "Offset",
          "begin": {
            "@type": "BeginAlignedCursor",
            "value": 12596
          },
          "end": {
            "@type": "BeginAlignedCursor",
            "value": 12815
          }
        }
      },
      "data": [
        {
          "@type": "AnnotationData",
          "@id": "47ED4703",
          "set": "Translation"
        },
        {
          "@type": "AnnotationData",
          "@id": "F5A84DFB",
          "set": "Translation"
        }
      ]
    },
    {
      "@type": "Annotation",
      "@id": "E3CF049E",
      "target": {
        "@type": "TextSelector",
        "resource": "DB0D",
        "offset": {
          "@type": "Offset",
          "begin": {
            "@type": "BeginAlignedCursor",
            "value": 12815
          },
          "end": {
            "@type": "BeginAlignedCursor",
            "value": 13022
          }
        }
      },
      "data": [
        {
          "@type": "AnnotationData",
          "@id": "CD32A4C0",
          "set": "Translation"
        },
        {
          "@type": "AnnotationData",
          "@id": "F5A84DFB",
          "set": "Translation"
        }
      ]
    },
    {
      "@type": "Annotation",
      "@id": "A643B87B",
      "target": {
        "@type": "TextSelector",
        "resource": "DB0D",
        "offset": {
          "@type": "Offset",
          "begin": {
            "@type": "BeginAlignedCursor",
            "value": 13022
          },
          "end": {
            "@type": "BeginAlignedCursor",
            "value": 13231
          }
        }
      },
      "data": [
        {
          "@type": "AnnotationData",
          "@id": "2520EC04",
          "set": "Translation"
        },
        {
          "@type": "AnnotationData",
          "@id": "F5A84DFB",
          "set": "Translation"
        }
      ]
    }
  ]
}